code2gist/__init__.py
code2gist/main.py
code2gist-1.1.4.dist-info/LICENSE
code2gist-1.1.4.dist-info/METADATA
code2gist-1.1.4.dist-info/WHEEL
code2gist-1.1.4.dist-info/entry_points.txt
code2gist-1.1.4.dist-info/top_level.txt
code2gist-1.1.4.dist-info/RECORD
