Metadata-Version: 2.1
Name: code2gist
Version: 1.1.4
Summary: Upload Python files in a directory to a GitHub Gist.
Author-email: Cameron Spears <flames.garish-0i@icloud.com>
License: GPL-3.0
Keywords: python,github,gist,upload
Classifier: Programming Language :: Python :: 3
Requires-Python: >=3.11.4
License-File: LICENSE
Requires-Dist: requests (>=2.28.2)
Requires-Dist: pathspec (>=0.11.1)
